Metadata-Version: 2.1
Name: PyJsonFiles
Version: 0.0.1
Summary: mythonm单mm建msonm件m/Mythonm single mm construction msonm piece M
Home-page: https://yangguang-gongzuoshi.top/wry/
Author: Ruoyu Wang
Author-email: wry2022@outlook.com
License: MIT License
Platform: UNKNOWN
Requires: codecs
